agreement_api/__init__.py
agreement_api/app.py
agreement_api/conftest.py
agreement_api/create_db.py
agreement_api/validators.py
agreement_api/controllers/__init__.py
agreement_api/controllers/agreement_controller.py
agreement_api/controllers/user_controller.py
agreement_api/models/__init__.py
agreement_api/models/agreement.py
agreement_api/models/user.py
agreement_api/models/utils.py
agreement_api/openapi/specification.yaml
agreement_api/test/__init__.py
agreement_api/test/controllers/__init__.py
agreement_api/test/controllers/test_agreement_controllers.py
agreement_api/test/controllers/test_user_controllers.py
agreement_api-0.0.1.dist-info/LICENSE
agreement_api-0.0.1.dist-info/METADATA
agreement_api-0.0.1.dist-info/WHEEL
agreement_api-0.0.1.dist-info/top_level.txt
agreement_api-0.0.1.dist-info/RECORD
